main/__init__.py
main/btc_eth.py
main/emoj.py
main/env.py
main/main.py
main/os.py
main/rmw.py
main/say.py
main/tg_login.py
main/ts.py
main/uu_id.py
pwsh_utils/__init__.py
pwsh_utils/crypto.py
pwsh_utils/env.py
pwsh_utils/md5.py
pwsh_utils/os.py
pwsh_utils/rmw.py
pwsh_utils/rnd_emoj.py
pwsh_utils/time.py
tg/__init__.py
tg/cli.py
tg/login.py
pwsh_utils-0.1.6.dist-info/entry_points.txt
pwsh_utils-0.1.6.dist-info/LICENSE
pwsh_utils-0.1.6.dist-info/METADATA
pwsh_utils-0.1.6.dist-info/WHEEL
pwsh_utils-0.1.6.dist-info/RECORD
